odoo/addons/ssi_accountant_report_revenue_recognition/README.rst
odoo/addons/ssi_accountant_report_revenue_recognition/__init__.py
odoo/addons/ssi_accountant_report_revenue_recognition/__manifest__.py
odoo/addons/ssi_accountant_report_revenue_recognition/models/__init__.py
odoo/addons/ssi_accountant_report_revenue_recognition/models/accountant_report_mixin.py
odoo/addons/ssi_accountant_report_revenue_recognition/static/description/icon.png
odoo/addons/ssi_accountant_report_revenue_recognition/views/accountant_report_mixin_views.xml
odoo14_addon_ssi_accountant_report_revenue_recognition-14.0.1.0.1.dev2.dist-info/METADATA
odoo14_addon_ssi_accountant_report_revenue_recognition-14.0.1.0.1.dev2.dist-info/WHEEL
odoo14_addon_ssi_accountant_report_revenue_recognition-14.0.1.0.1.dev2.dist-info/top_level.txt
odoo14_addon_ssi_accountant_report_revenue_recognition-14.0.1.0.1.dev2.dist-info/RECORD
